samternary/__init__.py
samternary/changeofbasis.py
samternary/ternary.py
ternary/__init__.py
ternary/changeofbasis.py
ternary/ternary.py
samternary-0.0.3.dist-info/LICENSE
samternary-0.0.3.dist-info/METADATA
samternary-0.0.3.dist-info/WHEEL
samternary-0.0.3.dist-info/top_level.txt
samternary-0.0.3.dist-info/RECORD
