Metadata-Version: 2.1
Name: samternary
Version: 0.0.3
Summary: package to plot ternary phase diagrams
Home-page: https://github.com/samueljmcameron/samternary
Author: Sam Cameron
Author-email: samuel.j.m.cameron@gmail.com
License: UNKNOWN
Platform: UNKNOWN
Classifier: Programming Language :: Python :: 3
Classifier: License :: OSI Approved :: GNU General Public License v3 (GPLv3)
Classifier: Operating System :: OS Independent
Requires-Python: >=3.3
Requires-Dist: matplotlib (>=3)
Requires-Dist: numpy
